fps_jupytercad/__init__.py
fps_jupytercad/main.py
fps_jupytercad/models.py
fps_jupytercad/py.typed
fps_jupytercad/routes.py
fps_jupytercad-0.3.3.dist-info/METADATA
fps_jupytercad-0.3.3.dist-info/WHEEL
fps_jupytercad-0.3.3.dist-info/entry_points.txt
fps_jupytercad-0.3.3.dist-info/licenses/COPYING.md
fps_jupytercad-0.3.3.dist-info/RECORD
